xxb/__init__.py
xxb/elegant/__init__.py
xxb/elegant/girl/__init__.py
xxb/elegant/girl/information.py
xxb/elegant/girl/message.py
dobuxing-0.2.dist-info/METADATA
dobuxing-0.2.dist-info/WHEEL
dobuxing-0.2.dist-info/top_level.txt
dobuxing-0.2.dist-info/RECORD
