Metadata-Version: 2.1
Name: dobuxing
Version: 0.2
Summary: 方家伟,黄之迷,谢心冰
Author: xxb
License: UNKNOWN
Platform: UNKNOWN
